<filename>25242681.jpg</filename>
<folder>/k/kitchen</folder>
<class>59</class>
<objects>
	<class>169</class>
	<polygon>
		<pt>
			<x>1</x>
			<y>121</y>
		</pt>
		<pt>
			<x>2</x>
			<y>121</y>
		</pt>
		<pt>
			<x>1</x>
			<y>67</y>
		</pt>
	</polygon>
	<bndbox>
		<xmin>1</xmin>
		<xmax>2</xmax>
		<ymin>67</ymin>
		<ymax>121</ymax>
	</bndbox>
</objects>
<objects>
	<class>169</class>
	<polygon>
		<pt>
			<x>128</x>
			<y>128</y>
		</pt>
		<pt>
			<x>118</x>
			<y>127</y>
		</pt>
		<pt>
			<x>93</x>
			<y>105</y>
		</pt>
		<pt>
			<x>66</x>
			<y>77</y>
		</pt>
		<pt>
			<x>65</x>
			<y>72</y>
		</pt>
		<pt>
			<x>64</x>
			<y>67</y>
		</pt>
		<pt>
			<x>66</x>
			<y>62</y>
		</pt>
		<pt>
			<x>64</x>
			<y>55</y>
		</pt>
		<pt>
			<x>61</x>
			<y>46</y>
		</pt>
		<pt>
			<x>75</x>
			<y>46</y>
		</pt>
		<pt>
			<x>75</x>
			<y>13</y>
		</pt>
		<pt>
			<x>82</x>
			<y>9</y>
		</pt>
		<pt>
			<x>81</x>
			<y>52</y>
		</pt>
		<pt>
			<x>120</x>
			<y>65</y>
		</pt>
		<pt>
			<x>128</x>
			<y>64</y>
		</pt>
	</polygon>
	<bndbox>
		<xmin>61</xmin>
		<xmax>128</xmax>
		<ymin>9</ymin>
		<ymax>128</ymax>
	</bndbox>
</objects>
<objects>
	<class>46</class>
	<polygon>
		<pt>
			<x>82</x>
			<y>1</y>
		</pt>
		<pt>
			<x>71</x>
			<y>1</y>
		</pt>
		<pt>
			<x>71</x>
			<y>3</y>
		</pt>
		<pt>
			<x>71</x>
			<y>8</y>
		</pt>
		<pt>
			<x>72</x>
			<y>11</y>
		</pt>
		<pt>
			<x>72</x>
			<y>12</y>
		</pt>
		<pt>
			<x>73</x>
			<y>13</y>
		</pt>
		<pt>
			<x>75</x>
			<y>12</y>
		</pt>
		<pt>
			<x>77</x>
			<y>11</y>
		</pt>
		<pt>
			<x>78</x>
			<y>11</y>
		</pt>
		<pt>
			<x>80</x>
			<y>10</y>
		</pt>
		<pt>
			<x>81</x>
			<y>10</y>
		</pt>
		<pt>
			<x>82</x>
			<y>9</y>
		</pt>
	</polygon>
	<bndbox>
		<xmin>71</xmin>
		<xmax>82</xmax>
		<ymin>1</ymin>
		<ymax>13</ymax>
	</bndbox>
</objects>
<objects>
	<class>174</class>
	<polygon>
		<pt>
			<x>59</x>
			<y>128</y>
		</pt>
		<pt>
			<x>51</x>
			<y>108</y>
		</pt>
		<pt>
			<x>51</x>
			<y>103</y>
		</pt>
		<pt>
			<x>52</x>
			<y>96</y>
		</pt>
		<pt>
			<x>53</x>
			<y>90</y>
		</pt>
		<pt>
			<x>53</x>
			<y>81</y>
		</pt>
		<pt>
			<x>53</x>
			<y>79</y>
		</pt>
		<pt>
			<x>58</x>
			<y>82</y>
		</pt>
		<pt>
			<x>62</x>
			<y>82</y>
		</pt>
		<pt>
			<x>64</x>
			<y>89</y>
		</pt>
		<pt>
			<x>66</x>
			<y>94</y>
		</pt>
		<pt>
			<x>67</x>
			<y>97</y>
		</pt>
		<pt>
			<x>67</x>
			<y>101</y>
		</pt>
		<pt>
			<x>69</x>
			<y>106</y>
		</pt>
		<pt>
			<x>70</x>
			<y>108</y>
		</pt>
		<pt>
			<x>71</x>
			<y>107</y>
		</pt>
		<pt>
			<x>72</x>
			<y>108</y>
		</pt>
		<pt>
			<x>74</x>
			<y>104</y>
		</pt>
		<pt>
			<x>75</x>
			<y>103</y>
		</pt>
		<pt>
			<x>75</x>
			<y>100</y>
		</pt>
		<pt>
			<x>73</x>
			<y>96</y>
		</pt>
		<pt>
			<x>71</x>
			<y>93</y>
		</pt>
		<pt>
			<x>69</x>
			<y>87</y>
		</pt>
		<pt>
			<x>68</x>
			<y>85</y>
		</pt>
		<pt>
			<x>67</x>
			<y>79</y>
		</pt>
		<pt>
			<x>67</x>
			<y>78</y>
		</pt>
		<pt>
			<x>118</x>
			<y>128</y>
		</pt>
	</polygon>
	<bndbox>
		<xmin>51</xmin>
		<xmax>118</xmax>
		<ymin>78</ymin>
		<ymax>128</ymax>
	</bndbox>
</objects>
<objects>
	<class>169</class>
	<polygon>
		<pt>
			<x>32</x>
			<y>1</y>
		</pt>
		<pt>
			<x>28</x>
			<y>1</y>
		</pt>
		<pt>
			<x>28</x>
			<y>43</y>
		</pt>
		<pt>
			<x>31</x>
			<y>39</y>
		</pt>
		<pt>
			<x>34</x>
			<y>36</y>
		</pt>
		<pt>
			<x>36</x>
			<y>34</y>
		</pt>
		<pt>
			<x>38</x>
			<y>33</y>
		</pt>
		<pt>
			<x>38</x>
			<y>26</y>
		</pt>
		<pt>
			<x>37</x>
			<y>25</y>
		</pt>
		<pt>
			<x>37</x>
			<y>21</y>
		</pt>
		<pt>
			<x>37</x>
			<y>18</y>
		</pt>
		<pt>
			<x>37</x>
			<y>18</y>
		</pt>
		<pt>
			<x>37</x>
			<y>14</y>
		</pt>
		<pt>
			<x>37</x>
			<y>9</y>
		</pt>
		<pt>
			<x>38</x>
			<y>4</y>
		</pt>
		<pt>
			<x>41</x>
			<y>1</y>
		</pt>
		<pt>
			<x>44</x>
			<y>2</y>
		</pt>
		<pt>
			<x>47</x>
			<y>5</y>
		</pt>
		<pt>
			<x>48</x>
			<y>9</y>
		</pt>
		<pt>
			<x>49</x>
			<y>15</y>
		</pt>
		<pt>
			<x>48</x>
			<y>19</y>
		</pt>
		<pt>
			<x>49</x>
			<y>20</y>
		</pt>
		<pt>
			<x>49</x>
			<y>23</y>
		</pt>
		<pt>
			<x>48</x>
			<y>28</y>
		</pt>
		<pt>
			<x>47</x>
			<y>32</y>
		</pt>
		<pt>
			<x>48</x>
			<y>33</y>
		</pt>
		<pt>
			<x>51</x>
			<y>33</y>
		</pt>
		<pt>
			<x>51</x>
			<y>1</y>
		</pt>
	</polygon>
	<bndbox>
		<xmin>28</xmin>
		<xmax>51</xmax>
		<ymin>1</ymin>
		<ymax>43</ymax>
	</bndbox>
</objects>
<objects>
	<class>17</class>
	<polygon>
		<pt>
			<x>71</x>
			<y>68</y>
		</pt>
		<pt>
			<x>71</x>
			<y>73</y>
		</pt>
		<pt>
			<x>72</x>
			<y>76</y>
		</pt>
		<pt>
			<x>71</x>
			<y>81</y>
		</pt>
		<pt>
			<x>69</x>
			<y>81</y>
		</pt>
		<pt>
			<x>69</x>
			<y>73</y>
		</pt>
		<pt>
			<x>69</x>
			<y>71</y>
		</pt>
		<pt>
			<x>70</x>
			<y>67</y>
		</pt>
	</polygon>
	<bndbox>
		<xmin>69</xmin>
		<xmax>72</xmax>
		<ymin>67</ymin>
		<ymax>81</ymax>
	</bndbox>
</objects>
<objects>
	<class>57</class>
	<polygon>
		<pt>
			<x>80</x>
			<y>99</y>
		</pt>
		<pt>
			<x>79</x>
			<y>94</y>
		</pt>
		<pt>
			<x>70</x>
			<y>84</y>
		</pt>
		<pt>
			<x>69</x>
			<y>84</y>
		</pt>
		<pt>
			<x>69</x>
			<y>86</y>
		</pt>
		<pt>
			<x>68</x>
			<y>85</y>
		</pt>
		<pt>
			<x>67</x>
			<y>82</y>
		</pt>
		<pt>
			<x>69</x>
			<y>82</y>
		</pt>
		<pt>
			<x>72</x>
			<y>82</y>
		</pt>
		<pt>
			<x>74</x>
			<y>85</y>
		</pt>
		<pt>
			<x>80</x>
			<y>91</y>
		</pt>
		<pt>
			<x>79</x>
			<y>86</y>
		</pt>
		<pt>
			<x>75</x>
			<y>85</y>
		</pt>
		<pt>
			<x>75</x>
			<y>83</y>
		</pt>
		<pt>
			<x>78</x>
			<y>85</y>
		</pt>
		<pt>
			<x>79</x>
			<y>83</y>
		</pt>
		<pt>
			<x>81</x>
			<y>82</y>
		</pt>
		<pt>
			<x>81</x>
			<y>85</y>
		</pt>
		<pt>
			<x>83</x>
			<y>86</y>
		</pt>
		<pt>
			<x>83</x>
			<y>88</y>
		</pt>
		<pt>
			<x>84</x>
			<y>99</y>
		</pt>
		<pt>
			<x>83</x>
			<y>100</y>
		</pt>
		<pt>
			<x>82</x>
			<y>98</y>
		</pt>
		<pt>
			<x>81</x>
			<y>98</y>
		</pt>
	</polygon>
	<bndbox>
		<xmin>67</xmin>
		<xmax>84</xmax>
		<ymin>82</ymin>
		<ymax>100</ymax>
	</bndbox>
</objects>
<objects>
	<class>87</class>
	<polygon>
		<pt>
			<x>114</x>
			<y>77</y>
		</pt>
		<pt>
			<x>118</x>
			<y>78</y>
		</pt>
		<pt>
			<x>117</x>
			<y>88</y>
		</pt>
		<pt>
			<x>113</x>
			<y>87</y>
		</pt>
	</polygon>
	<bndbox>
		<xmin>113</xmin>
		<xmax>118</xmax>
		<ymin>77</ymin>
		<ymax>88</ymax>
	</bndbox>
</objects>
<objects>
	<class>152</class>
	<polygon>
		<pt>
			<x>104</x>
			<y>71</y>
		</pt>
		<pt>
			<x>103</x>
			<y>86</y>
		</pt>
		<pt>
			<x>109</x>
			<y>90</y>
		</pt>
		<pt>
			<x>111</x>
			<y>89</y>
		</pt>
		<pt>
			<x>112</x>
			<y>75</y>
		</pt>
	</polygon>
	<bndbox>
		<xmin>103</xmin>
		<xmax>112</xmax>
		<ymin>71</ymin>
		<ymax>90</ymax>
	</bndbox>
</objects>
<objects>
	<class>19</class>
	<polygon>
		<pt>
			<x>119</x>
			<y>87</y>
		</pt>
		<pt>
			<x>115</x>
			<y>87</y>
		</pt>
		<pt>
			<x>112</x>
			<y>88</y>
		</pt>
		<pt>
			<x>110</x>
			<y>89</y>
		</pt>
		<pt>
			<x>108</x>
			<y>92</y>
		</pt>
		<pt>
			<x>108</x>
			<y>101</y>
		</pt>
		<pt>
			<x>110</x>
			<y>109</y>
		</pt>
		<pt>
			<x>113</x>
			<y>113</y>
		</pt>
		<pt>
			<x>116</x>
			<y>117</y>
		</pt>
		<pt>
			<x>117</x>
			<y>122</y>
		</pt>
		<pt>
			<x>118</x>
			<y>125</y>
		</pt>
		<pt>
			<x>119</x>
			<y>128</y>
		</pt>
		<pt>
			<x>124</x>
			<y>128</y>
		</pt>
		<pt>
			<x>124</x>
			<y>124</y>
		</pt>
		<pt>
			<x>125</x>
			<y>123</y>
		</pt>
		<pt>
			<x>126</x>
			<y>120</y>
		</pt>
		<pt>
			<x>128</x>
			<y>120</y>
		</pt>
		<pt>
			<x>128</x>
			<y>89</y>
		</pt>
		<pt>
			<x>123</x>
			<y>88</y>
		</pt>
	</polygon>
	<bndbox>
		<xmin>108</xmin>
		<xmax>128</xmax>
		<ymin>87</ymin>
		<ymax>128</ymax>
	</bndbox>
</objects>
<objects>
	<class>61</class>
	<polygon>
		<pt>
			<x>1</x>
			<y>128</y>
		</pt>
		<pt>
			<x>1</x>
			<y>121</y>
		</pt>
		<pt>
			<x>25</x>
			<y>117</y>
		</pt>
		<pt>
			<x>25</x>
			<y>128</y>
		</pt>
	</polygon>
	<bndbox>
		<xmin>1</xmin>
		<xmax>25</xmax>
		<ymin>117</ymin>
		<ymax>128</ymax>
	</bndbox>
</objects>
<objects>
	<class>28</class>
	<polygon>
		<pt>
			<x>128</x>
			<y>1</y>
		</pt>
		<pt>
			<x>82</x>
			<y>1</y>
		</pt>
		<pt>
			<x>81</x>
			<y>52</y>
		</pt>
		<pt>
			<x>121</x>
			<y>65</y>
		</pt>
		<pt>
			<x>128</x>
			<y>64</y>
		</pt>
	</polygon>
	<bndbox>
		<xmin>81</xmin>
		<xmax>128</xmax>
		<ymin>1</ymin>
		<ymax>65</ymax>
	</bndbox>
</objects>
